dash_high_charts/HighChart.py
dash_high_charts/__init__.py
dash_high_charts/_imports_.py
dash_high_charts/async-HighChart.js
dash_high_charts/async-HighChart.js.map
dash_high_charts/dash_high_charts.min.js
dash_high_charts/dash_high_charts.min.js.map
dash_high_charts/metadata.json
dash_high_charts/package-info.json
dash_high_charts-0.0.1rc0.dist-info/LICENSE
dash_high_charts-0.0.1rc0.dist-info/METADATA
dash_high_charts-0.0.1rc0.dist-info/WHEEL
dash_high_charts-0.0.1rc0.dist-info/top_level.txt
dash_high_charts-0.0.1rc0.dist-info/RECORD
