Metadata-Version: 2.1
Name: dash_high_charts
Version: 0.0.1rc0
Summary: HighCharts wrapper for Plotly Dash
Author: Laxman Bablani <laxman@bablani.org>
License: MIT
Classifier: Framework :: Dash
License-File: LICENSE
